geoestatedev/__init__.py
geoestatedev/common.py
geoestatedev/geoestatedev.py
geoestatedev-0.0.1.dist-info/licenses/LICENSE
geoestatedev-0.0.1.dist-info/METADATA
geoestatedev-0.0.1.dist-info/WHEEL
geoestatedev-0.0.1.dist-info/entry_points.txt
geoestatedev-0.0.1.dist-info/top_level.txt
geoestatedev-0.0.1.dist-info/RECORD
